{
  "pn": "FUSE-0.5A-5X20",
  "brand": "Honeywell",
  "identity_status": "not_found",
  "source_url": null,
  "source_type": null,
  "source_domain": null,
  "source_strength": null,
  "pn_match_type": "not_found",
  "product_name": null,
  "product_type": null,
  "datasheet_url": null,
  "confidence": "high",
  "raw_response": "```json\n{\n  \"pn_found\": false,\n  \"match_type\": \"not_found\",\n  \"product_name\": null,\n  \"product_type\": null,\n  \"source_url\": null,\n  \"source_domain\": null,\n  \"source_type\": null,\n  \"datasheet_url\": null,\n  \"confidence\": \"high\",\n  \"notes\": \"The exact part number 'Honeywell FUSE-0.5A-5X20' was not found on the manufacturer's official website or authorized distributors as a standalone product. While some distributors list Honeywell fuses with similar specifications (e.g., 0.5A, 5x20mm), they are associated with different Honeywell internal part numbers (e.g., 952088). The provided part number appears to be a generic description rather than an official Honeywell product identifier.\"\n}\n```",
  "accept_for_pipeline": false,
  "reject_reason": "no match or inferred only"
}