{
  "packet_version": "v1",
  "task_id": "enrichment_research_S10010",
  "domain": "enrichment",
  "entity_type": "pn",
  "entity_id": "S10010",
  "brand_hint": "Honeywell",
  "goal": "Close unresolved enrichment gaps for PN S10010 (Honeywell)",
  "research_reason": "identity_weak",
  "priority": "low",
  "questions_to_resolve": [
    "Confirm the exact product identity for Honeywell PN=S10010",
    "What is the full product name and product family for Honeywell S10010?",
    "Is S10010 a current, discontinued, or superseded part number?",
    "Provide any relevant Russian-language product description for Honeywell S10010"
  ],
  "current_state": {
    "card_status": "DRAFT_ONLY",
    "identity_level": "weak",
    "photo_verdict": "KEEP",
    "price_status": "no_price_found",
    "price_source_url": "https://www.bolasystems.com/honeywell-smartact-spring-return-actuator-s10010-10nm-24-vac-0-10v",
    "category_mismatch": false,
    "overall_confidence": "VERY_LOW",
    "review_reasons": [
      "IDENTITY_WEAK",
      "NO_IMAGE_EVIDENCE",
      "NO_PRICE_EVIDENCE",
      "PDF_NOT_EXACT_CONFIRMED"
    ]
  },
  "known_facts": {
    "brand": "Honeywell",
    "name": "Привод заслонки 10NM 24V S10010",
    "assembled_title": "Привод Honeywell S10010",
    "expected_category": "Привод",
    "our_price_raw": "8870,00",
    "has_content_seed": true,
    "price_currency": null,
    "price_native_value": null,
    "price_rub": null,
    "existing_source_url": "https://www.bolasystems.com/honeywell-smartact-spring-return-actuator-s10010-10nm-24-vac-0-10v",
    "pn_variants": []
  },
  "existing_evidence_refs": [
    "downloads/evidence/evidence_S10010.json"
  ],
  "constraints": [
    "Use public web evidence only",
    "Do not use xlsx price as market price",
    "Do not invent specs if not found",
    "If uncertain, return ambiguity explicitly",
    "Prefer exact PN evidence over family-level evidence",
    "Cite specific URLs for any claim"
  ],
  "required_output": {
    "identity": true,
    "title_ru": true,
    "description_ru": true,
    "category": true,
    "price_assessment": true,
    "photo_assessment": true,
    "specs_assessment": true,
    "citations_required": true,
    "ambiguities_required": true
  },
  "generated_at": "2026-04-08T10:04:20.528412Z"
}