{
  "CM010610": {
    "pn": "CM010610",
    "brand": "ДКС",
    "title": "Винт крестообразный шлиц М6х10",
    "price": "9",
    "currency": "RUB",
    "photo_url": "",
    "specs": {
      "diameter": "6 mm",
      "length": "10 mm",
      "thread_type": "Метрическая (M6)",
      "material": "Сталь",
      "coating": "Гальваническое цинковое покрытие",
      "head_shape": "Сферическая головка",
      "slot_type": "Гладкая",
      "color": "Светло-серый",
      "grade": "5.8",
      "weight": "4 g",
      "climate_rating": "УХЛ2",
      "self_drilling": "Да",
      "hardened": "Да",
      "sharp_tip": "Да"
    },
    "ean": "",
    "category_path": "Корпусные и установочные изделия > Крепежные элементы > Винты > DKC",
    "datasheet_url": "pdf, 182 КБ",
    "is_correct_product": true,
    "_source_url": "https://www.chipdip.ru/product0/8000757816"
  }
}