{
  "result_version": "v1",
  "task_id": "enrichment_research_101411",
  "entity_id": "101411",
  "research_reason": "identity_weak",
  "priority": "high",
  "final_recommendation": {
    "confidence": "low",
    "photo_url": "—",
    "sources": [
      {
        "url": "—",
        "type": "—",
        "domain": "",
        "supports": [
          "identity",
          "photo"
        ]
      }
    ]
  },
  "sources": [
    {
      "url": "—",
      "type": "—",
      "domain": "",
      "supports": [
        "identity",
        "photo"
      ]
    }
  ],
  "confidence": "low",
  "parse_error": "",
  "timestamp": "2026-04-08T20:48:25.787057Z",
  "provider": "unknown",
  "model": "unknown",
  "raw_response_length": 21,
  "cost_usd": 0.0,
  "web_search_used": true,
  "dr_source_file": "compass_artifact_wf-7345a519-7322-401f-9d32-702764e5d9bc_text_markdown.md"
}